serial/__init__.py
serial/errors.py
serial/hooks.py
serial/marshal.py
serial/meta.py
serial/model.py
serial/properties.py
serial/request.py
serial/test.py
serial/abc/__init__.py
serial/abc/model.py
serial/abc/properties.py
serial/utilities/__init__.py
serial/utilities/compatibility.py
serial-0.0.97.dist-info/METADATA
serial-0.0.97.dist-info/WHEEL
serial-0.0.97.dist-info/top_level.txt
serial-0.0.97.dist-info/RECORD
